beacon/__init__.py
beacon/adict.py
beacon/parser.py
beacon/scope.py
beacon/utils.py
beacon/xyz.py
beacon/db_routers/__init__.py
beacon/db_routers/sql/__init__.py
beacon/db_routers/sql/manager.py
beacon/db_routers/sql/schema.py
beacon/db_routers 2/__init__.py
beacon/db_routers 2/sql/__init__.py
beacon/db_routers 2/sql/manager.py
beacon/db_routers 2/sql/schema.py
beacon/hyperopt/__init__.py
beacon/hyperopt/base.py
beacon/hyperopt/hyperband.py
beacon_python-2.0.0.dist-info/licenses/LICENSE
beacon_python-2.0.0.dist-info/METADATA
beacon_python-2.0.0.dist-info/WHEEL
beacon_python-2.0.0.dist-info/top_level.txt
beacon_python-2.0.0.dist-info/RECORD
